engineioN/__init__.py
engineioN/asyncio_client.py
engineioN/client.py
engineioN/exceptions.py
engineioN/json.py
engineioN/packet.py
engineioN/payload.py
nertivia/__init__.py
nertivia/bot.py
nertivia/cache_nertivia_data.py
nertivia/channel.py
nertivia/client.py
nertivia/http.py
nertivia/message.py
nertivia/server.py
nertivia/user.py
socketioN/__init__.py
socketioN/asyncio_client.py
socketioN/client.py
socketioN/exceptions.py
socketioN/namespace.py
socketioN/packet.py
nertivia.py-0.2.9.dist-info/LICENSE
nertivia.py-0.2.9.dist-info/METADATA
nertivia.py-0.2.9.dist-info/WHEEL
nertivia.py-0.2.9.dist-info/top_level.txt
nertivia.py-0.2.9.dist-info/RECORD
